[
  {
    "id": 1,
    "name": "कंपनी2",
    "info": "लोरेम इप्सम प्रिंटिंग और टाइपसेटिंग उद्योग का केवल डमी टेक्स्ट है। लोरेम इप्सम 1500 के दशक से उद्योग का मानक डमी पाठ रहा है, 1500 के दशक से उद्योग का मानक डमी पाठ रहा है,"
  },
  {
    "id": 2,
    "name": "कंपनी3",
    "info": "लोरेम इप्सम प्रिंटिंग और टाइपसेटिंग उद्योग का केवल डमी टेक्स्ट है। लोरेम इप्सम 1500 के दशक से उद्योग का मानक डमी पाठ रहा है, 1500 के दशक से उद्योग का मानक डमी पाठ रहा है,"
  },
  {
    "id": 3,
    "name": "कंपनी4",
    "info": "लोरेम इप्सम प्रिंटिंग और टाइपसेटिंग उद्योग का केवल डमी टेक्स्ट है। लोरेम इप्सम 1500 के दशक से उद्योग का मानक डमी पाठ रहा है, 1500 के दशक से उद्योग का मानक डमी पाठ रहा है,"
  },
  {
    "id": 4,
    "name": "परीक्षण 1",
    "info": "परीक्षण जानकारी निवेशक कंपनी"
  }
]